is_number/__init__.py
is_number/_version.py
is_number/is_number.py
is_numer-0.0.5.dist-info/LICENSE
is_numer-0.0.5.dist-info/METADATA
is_numer-0.0.5.dist-info/WHEEL
is_numer-0.0.5.dist-info/top_level.txt
is_numer-0.0.5.dist-info/RECORD
