Metadata-Version: 2.1
Name: is-numer
Version: 0.0.5
Summary: A Python library to determine if something is a number.
Author: AKV
Author-email: ayushverma@vassarlabs.com
Classifier: Programming Language :: Python :: 3
Classifier: License :: OSI Approved :: MIT License
Classifier: Operating System :: OS Independent
Requires-Python: >=3.6
License-File: LICENSE
